{
  "result": {
    "item": "harvestcraft:haggisitem"
  },

  "ingredients": [
    {
      "type": "forge:ore_dict",
      "ore": "toolPot"
    },
    {
      "item": "minecraft:rotten_flesh"
    },
    {
      "item": "minecraft:spider_eye"
    },
    {
      "type": "forge:ore_dict",
      "ore": "cropOnion"
    },
    {
      "type": "forge:ore_dict",
      "ore": "cropOats"
    },
    {
      "type": "forge:ore_dict",
      "ore": "itemSalt"
    },
    {
      "type": "forge:ore_dict",
      "ore": "foodBlackpepper"
    },
    {
      "type": "forge:ore_dict",
      "ore": "cropSpiceleaf"
    }
  ],
  "type": "forge:ore_shapeless"
}