{
  "result": {
    "item": "harvestcraft:meatloafitem"
  },

  "ingredients": [
    {
      "type": "forge:ore_dict",
      "ore": "toolBakeware"
    },
    {
      "type": "forge:ore_dict",
      "ore": "listAllbeefraw"
    },
    {
      "type": "forge:ore_dict",
      "ore": "bread"
    },
    {
      "type": "forge:ore_dict",
      "ore": "cropOnion"
    },
    {
      "type": "forge:ore_dict",
      "ore": "cropGarlic"
    },
    {
      "type": "forge:ore_dict",
      "ore": "foodKetchup"
    }
  ],
  "type": "forge:ore_shapeless"
}
